{
    "1":{
        "name":"박미라",
        "gender":"여",
        "age":24,
        "resume":"현)전정대 의장"
    },
    "2":{
        "name":"하지민",
        "gender":"여",
        "age":23,
        "resume":"전)Sw학생회"
    },
    "3":{
        "name":"장정환",
        "gender":"남",
        "age":27,
        "resume":"SW학부 학생"
    },
    "4":{
        "name":"홍길동",
        "gender":"남",
        "age":35,
        "resume":"의적"
    },
    "5":{
        "name":"이몽룡",
        "gender":"남",
        "age":28,
        "resume":"암행어사"
    }
}
